posture_agent/__init__.py
posture_agent/main.py
posture_agent/collectors/__init__.py
posture_agent/collectors/ai_tools.py
posture_agent/collectors/base.py
posture_agent/collectors/dev_tools.py
posture_agent/collectors/extensions.py
posture_agent/collectors/ides.py
posture_agent/collectors/machine.py
posture_agent/collectors/mcp_servers.py
posture_agent/collectors/package_managers.py
posture_agent/collectors/security.py
posture_agent/core/__init__.py
posture_agent/core/config.py
posture_agent/models/__init__.py
posture_agent/models/report.py
posture_agent/services/__init__.py
posture_agent/services/fingerprint.py
posture_agent/services/reporter.py
posture_agent/utils/__init__.py
posture_agent/utils/shell.py
intercept_agent-0.3.0.dist-info/METADATA
intercept_agent-0.3.0.dist-info/WHEEL
intercept_agent-0.3.0.dist-info/entry_points.txt
intercept_agent-0.3.0.dist-info/RECORD
