Metadata-Version: 2.4
Name: intercept-agent
Version: 0.3.0
Summary: Intercept Developer Posture Agent - collects developer environment data
Requires-Python: >=3.12
Requires-Dist: click>=8.1.0
Requires-Dist: httpx>=0.28.0
Requires-Dist: pydantic>=2.10.0
Requires-Dist: pyyaml>=6.0.0
